cafs_cache_cdn_client/__init__.py
cafs_cache_cdn_client/cafs/README.md
cafs_cache_cdn_client/cafs/__init__.py
cafs_cache_cdn_client/cafs/blob/__init__.py
cafs_cache_cdn_client/cafs/blob/hash_.py
cafs_cache_cdn_client/cafs/blob/package.py
cafs_cache_cdn_client/cafs/blob/utils.py
cafs_cache_cdn_client/cafs/client.py
cafs_cache_cdn_client/cafs/exceptions.py
cafs_cache_cdn_client/cafs/types.py
cafs_cache_cdn_client/client.py
cafs_cache_cdn_client/file_utils.py
cafs_cache_cdn_client/repo/__init__.py
cafs_cache_cdn_client/repo/client.py
cafs_cache_cdn_client/repo/datatypes.py
cafs_cache_cdn_client-1.0.11.dist-info/METADATA
cafs_cache_cdn_client-1.0.11.dist-info/WHEEL
cafs_cache_cdn_client-1.0.11.dist-info/RECORD
