Metadata-Version: 2.3
Name: cafs-cache-cdn-client
Version: 1.0.11
Summary: Async Cache CDN client implementation
Keywords: cafs,cache
Author: Konstantin Belov
Author-email: k.belov@gaijin.team
Requires-Python: >=3.11,<4.0
Classifier: License :: OSI Approved :: MIT License
Classifier: Development Status :: 4 - Beta
Classifier: Programming Language :: Python :: 3.11
Classifier: Programming Language :: Python :: 3.12
Classifier: Programming Language :: Python :: 3.13
Classifier: Topic :: Software Development :: Libraries :: Python Modules
Requires-Dist: aiofiles
Requires-Dist: aiohttp
Requires-Dist: blake3
Requires-Dist: zstandard
